import{_ as i}from"./_plugin-vue_export-helper.cdc0426e.js";import{o as d,c as l,a as e,e as o,b as a,d as s,r as v}from"./app.acc1cb71.js";const c={},r=a("\u6765\u6E90\uFF1A "),t={href:"https://dzone.com/articles/introduction-to-java-bytecode",target:"_blank",rel:"noopener noreferrer"},u=a("https://dzone.com/articles/introduction-to-java-bytecode"),m=s(`<p>\u8FD9\u662F\u4E00\u904D\u76F8\u5BF9\u6765\u8BF4\u6BD4\u8F83\u7B80\u5355\u7684Java \u5B57\u8282\u7801\u5165\u95E8\u6587\u7AE0\uFF0C\u4E00\u5F00\u59CB\u4F5C\u8005\u8BB2\u5230\u4E86\u9605\u8BFBJava \u5B57\u8282\u7801\u6BD4\u8F83\u67AF\u71E5\u65E0\u5473\uFF0C\u4F46\u662F\u901A\u8FC7\u81EA\u5DF1\u7684\u6545\u4E8B\u8BF4\u660E\u4E86\u5B57\u8282\u7801\u7684\u4F5C\u7528\uFF0C\u4E8B\u60C5\u662F\u8FD9\u6837\u7684\uFF0C\u8FD9\u54E5\u4EEC\u5728\u5F88\u65E9\u4E4B\u524D\u505A\u4E86\u4E00\u6B21\u529F\u80FD\u53D8\u66F4\uFF0C\u76EE\u7684\u662F\u4E3A\u4E86\u6D4B\u8BD5\u4FEE\u590D\u4E00\u4E2A\u6F5C\u5728\u7684\u6027\u80FD\u95EE\u9898, \u5E76\u4E14\u6253\u597D\u4E86 JAR \u5305\u90E8\u7F72\u5230\u670D\u52A1\u5668\u4E0A\u3002\u4E0D\u5E78\u7684\u662F\uFF0C\u4ED6\u5E76\u6CA1\u6709\u5C06\u6E90\u7801\u63D0\u4EA4\u5230\u7248\u672C\u63A7\u5236\u7CFB\u7EDF\u4E0A\uFF0C\u540E\u6765\u4E0D\u77E5\u4EC0\u4E48\u539F\u56E0\u8FD9\u6BB5\u4EE3\u7801\u627E\u4E0D\u5230\u4E86\uFF0C\u4E00\u70B9\u75D5\u8FF9\u90FD\u6CA1\u6709\u4E86\uFF08\u505A\u4E86\u4EC0\u4E48\u65B0\u7684\u529F\u80FD\uFF0C\u8BB0\u5F97\u4E00\u5B9A\u8981\u63D0\u4EA4\u4EE3\u7801\u5230Git \u4E0A\uFF09\uFF0C\u51E0\u4E2A\u6708\u540E\u5F53\u4ED6\u60F3\u7528\u5230\u90A3\u6BB5\u4EE3\u7801\u7684\u65F6\u5019\uFF0C\u60B2\u5267\u5C31\u53D1\u751F\u4E86\u3002\u8FD8\u597D\u8FD9\u54E5\u4EEC\u5728\u8FDC\u7A0B\u673A\u5668\u4E0A\u90E8\u7F72\u7684 JAR \u5305\u8FD8\u5728\uFF0C\u4E8E\u662F\u4ED6\u7528\u53CD\u7F16\u8BD1\u7684\u5DE5\u5177\u6765\u627E\u5230\u6E90\u7801\uFF0C\u66F4\u4E0D\u5E78\u7684\u662F\uFF0C\u53CD\u7F16\u8BD1\u5DE5\u5177\u5728\u5173\u952E\u7684<code>Class</code>\u4E0A\u5D29\u6E83\u4E86\uFF0C\u4E5F\u5C31\u662F\u4ED6\u6B63\u597D\u8981\u627E\u7684\u5173\u952E\u4EE3\u7801!</p><p>\u5728\u5C1D\u8BD5\u4E86\u65E0\u6570\u6B21\u4E4B\u540E\uFF0C\u4ED6\u653E\u5F03\u4E86\u7528\u53CD\u7F16\u8BD1\u5DE5\u5177\uFF0C\u6240\u5E78\u7684\u662F\uFF0C\u8FD9\u54E5\u4EEC\u6BD4\u8F83\u719F\u6089 Java \u5B57\u8282\u7801\uFF0C\u5E76\u4E14\u8FD8\u8BB0\u5F97\u4ED6\u7684\u4EE3\u7801\u662F\u4ECE\u54EA\u5F00\u59CB\u7684\uFF0C\u4E8E\u662F\u901A\u8FC7\u9605\u8BFBJava \u5B57\u8282\u7801\u77E5\u9053\u4E86\u81EA\u5DF1\u505A\u4E86\u54EA\u4E9B\u4FEE\u6539\uFF0C\u6700\u540E\u4ED6\u75DB\u82E6\u7684\u603B\u7ED3\u5230 \u{1F606}</p><p><code>I made sure to learn from my mistake and preserve them this time!</code></p><p>Java \u5B57\u8282\u7801\u662F\u4E00\u79CD\u4ECB\u4E8E\u9AD8\u7EA7\u8BED\u8A00\u548C\u5E95\u5C42\u4EE3\u7801\u4E4B\u95F4\u7684\u4E2D\u95F4\u4EA7\u7269\uFF0C\u5B83\u5C4F\u853D\u4E86\u64CD\u4F5C\u7CFB\u7EDF\u6307\u4EE4\u67B6\u6784\u4E4B\u95F4\u7684\u533A\u522B\uFF0C\u5B9A\u4E49\u4E86JVM \u865A\u62DF\u673A\u80FD\u591F\u8BC6\u522B\u7684\u7EDF\u4E00\u683C\u5F0F\uFF0C\u5BF9\u4E8E\u6240\u6709\u5E73\u53F0\u6765\u8BF4\uFF0C\u5B57\u8282\u7801\u90FD\u662F\u901A\u7528\u7684\u3002</p><p>Java \u5B57\u8282\u7801\u6709\u70B9\u7C7B\u4F3C\u4E8E\u673A\u5668\u7801\uFF0C\u4F46\u662F\u5374\u66F4\u4E3A\u7B80\u5355\u6613\u61C2\uFF0C\u8FD9\u5F97\u76CA\u4E8E JVM \u865A\u62DF\u673A\u4F7F\u7528\u7684\u6307\u4EE4\u96C6\u67B6\u6784\u6BD4\u8F83\u7B80\u5355\uFF0C\u5E76\u4E14\u6709\u5341\u5206\u5B8C\u5584\u7684\u6587\u6863\u3002</p><p>\u6587\u7AE0\u7B80\u5355\u4ECB\u7ECD\u4E86\u4E00\u4E0B JVM \u865A\u62DF\u673A\u652F\u6301\u7684\u6570\u636E\u7C7B\u578B\uFF0C\u6BD4\u5982\u6211\u4EEC\u5E38\u89C1\u7684\u57FA\u672C\u6570\u636E\u7C7B\u578B\uFF1A<code>byte</code>\u3001<code>short</code> \u3001<code>int</code> \u3001<code>long</code> \u3001<code>char</code> \u3001<code>float</code>\u3001 <code>double</code> \u3001<code>boolean</code>\u4EE5\u53CA<code>returnAddress</code>,\u8FD8\u6709\u5F15\u7528\u7C7B\u578B\uFF0C\u5305\u62EC<code>class</code>,<code>array</code>,<code>interface</code>. \u5BF9<code>boolean</code>\u7C7B\u578B\u6765\u8BF4\u5E76\u6CA1\u6709\u76F8\u5BF9\u5E94\u7684\u5B57\u8282\u7801\u6307\u4EE4\uFF0C\u800C\u662F\u8F6C\u6362\u6210<code>int</code> \u7C7B\u578B\u6765\u64CD\u4F5C\uFF0C\u9664\u4E86<code>returnAddress</code>\u4EE3\u8868\u6307\u5411\u4E0B\u4E00\u4E2A\u6307\u4EE4\u5916\uFF0C\u5176\u4ED6\u7C7B\u578B\u90FD\u53EF\u4EE5\u5728 Java \u4E2D\u627E\u5230\u5BF9\u5E94\u7684\u7C7B\u578B.</p><p>\u5B57\u8282\u7801\u6307\u4EE4\u96C6\u7684\u7B80\u5316\u5F97\u76CA\u4E8E<code>Sun</code>\u516C\u53F8\u91C7\u7528\u4E86\u57FA\u4E8E\u6808\u7684\u865A\u62DF\u673A\u67B6\u6784\uFF0C\u8FD9\u662F\u4E00\u79CD\u4E0D\u540C\u4E8E\u57FA\u4E8E\u5BC4\u5B58\u5668\u7684\u67B6\u6784\u3002JVM \u8FDB\u7A0B\u5185\u5B58\u5212\u5206\u6210\u4E86\u4E0D\u540C\u7684\u5185\u5B58\u533A\u57DF\uFF0C\u4F46\u662F\u5374\u53EA\u8981\u68C0\u67E5 JVM \u865A\u62DF\u673A\u6808\u5C31\u80FD\u6EE1\u8DB3\u9075\u5FAA\u5B57\u8282\u7801\u7684\u6307\u4EE4\u96C6\u7684\u8981\u6C42\u3002</p><p>\u5BF9\u4E8EJVM \u865A\u62DF\u673A\u5185\u5B58\u7684\u5212\u5206\u7684\u4ECB\u7ECD\uFF0C\u8FD9\u7BC7\u6587\u7AE0\u8BF4\u7684\u6BD4\u8F83\u7B80\u5355\uFF0C\u60F3\u4E86\u89E3\u66F4\u591A\u53EF\u4EE5\u9605\u8BFB\u5468\u5FD7\u660E\u7684\u300A\u6DF1\u5165\u7406\u89E3Java\u865A\u62DF\u673A(\u7B2C\u4E09\u7248)\u300B\u4EE5\u53CA JVM \u7684\u865A\u62DF\u673A\u89C4\u8303\u3002</p><p>\u7136\u540E\u4F5C\u8005\u4E3E\u4E86\u51E0\u4E2A\u7B80\u5355\u7684Java \u4EE3\u7801\u7F16\u8BD1\u540E\u7684\u5B57\u8282\u7801\uFF0C\u5206\u6790\u4E86\u5B57\u8282\u7801\u662F\u5982\u4F55\u64CD\u4F5C\u672C\u5730\u53D8\u91CF\u8868\u548C\u64CD\u4F5C\u6570\u6808\u7684\uFF0C\u8FD9\u91CC\u8981\u6CE8\u610F\u7684\u662F<code>invokestatic</code>\u6307\u4EE4\u5982\u4F55\u8FDB\u884C\u7684\u65B9\u6CD5\u8C03\u7528\uFF0C\u5C06\u64CD\u4F5C\u6570\u6808\u4E0A\u7684\u6570\u636E\u4F20\u9012\u7ED9\u4E0B\u4E00\u4E2A\u6808\u5E27\u3002\u8FD8\u6709\u5C31\u662F<code>new</code>\u4E00\u4E2A\u5BF9\u8C61\u7684\u65F6\u5019\u4F1A\u6D89\u53CA\u5230\u7684\u6307\u4EE4\uFF0C\u5148\u662F<code>new</code>\u6307\u4EE4\u521B\u5EFA\u4E00\u4E2A\u5728\u5806\u4E0A\u7684\u5BF9\u8C61\u4EE5\u53CA\u5C06\u5F15\u7528\u5BF9\u8C61<code>push </code>\u5230\u64CD\u4F5C\u6570\u6808\u9876\uFF0C\u7136\u540E<code>dup</code>\u6307\u4EE4\u62F7\u8D1D\u4E86\u8FD9\u4E2A\u5F15\u7528\uFF0C\u4E5F\u5C31\u662F\u8BF4\u6B64\u65F6\u5728\u64CD\u4F5C\u6570\u6808\u4E0A\u67092\u4E2A\u5B9E\u4F8B\u5BF9\u8C61\u7684\u5F15\u7528\uFF0C\u7136\u540E\u538B\u5165\u6784\u9020\u51FD\u6570\u9700\u8981\u7684\u53C2\u6570\u548C\u5B9E\u4F8B\u5F15\u7528\uFF0C\u7528<code>invokespecial</code>\u8C03\u7528\u6784\u9020\u51FD\u6570\u3002</p><p>\u6700\u540E\u4F5C\u8005\u8BF4\u660E\uFF0C\u4E00\u822C\u60C5\u51B5\u4E0B\u5E76\u4E0D\u9700\u8981\u5B8C\u5168\u638C\u63E1\u5B57\u8282\u7801\u6307\u4EE4\u7684\u8BE6\u7EC6\u7528\u6CD5\u548C\u5177\u4F53\u7684\u6307\u4EE4\u6D41\u7A0B\u6765\u8BFB\u61C2\u7A0B\u5E8F\u6267\u884C\u7684\u662F\u4EC0\u4E48\u3002\u6BD4\u5982\u4E3A\u4E86\u641E\u6E05\u695A\u4F7F\u7528 Java Stream \u6765\u8BFB\u53D6\u6587\u4EF6\u7684\u65F6\u5019\u662F\u5426\u4F1A\u6B63\u786E\u5173\u95ED\u6D41\uFF0C\u901A\u8FC7\u67E5\u770B\u5B57\u8282\u7801\u53D1\u73B0\u6709\u4E00\u6BB5\u7C7B\u4F3C\u4E8E <code>try-with-resource</code>\u7684\u903B\u8F91\u5C31\u53EF\u4EE5\u77E5\u9053\u7ED3\u679C\u4E86\u3002</p><div class="language-Java ext-Java line-numbers-mode"><pre class="language-Java"><code>public static void main(java.lang.String[]) throws java.lang.Exception;
 descriptor: ([Ljava/lang/String;)V
 flags: (0x0009) ACC_PUBLIC, ACC_STATIC
 Code:
   stack=2, locals=8, args_size=1
      0: ldc           #2                  // class test/Test
      2: ldc           #3                  // String input.txt
      4: invokevirtual #4                  // Method java/lang/Class.getResource:(Ljava/lang/String;)Ljava/net/URL;
      7: invokevirtual #5                  // Method java/net/URL.toURI:()Ljava/net/URI;
     10: invokestatic  #6                  // Method java/nio/file/Paths.get:(Ljava/net/URI;)Ljava/nio/file/Path;
     13: astore_1
     14: new           #7                  // class java/lang/StringBuilder
     17: dup
     18: invokespecial #8                  // Method java/lang/StringBuilder.&quot;&lt;init&gt;&quot;:()V
     21: astore_2
     22: aload_1
     23: invokestatic  #9                  // Method java/nio/file/Files.lines:(Ljava/nio/file/Path;)Ljava/util/stream/Stream;
     26: astore_3
     27: aconst_null
     28: astore        4
     30: aload_3
     31: aload_2
     32: invokedynamic #10,  0             // InvokeDynamic #0:accept:(Ljava/lang/StringBuilder;)Ljava/util/function/Consumer;
     37: invokeinterface #11,  2           // InterfaceMethod java/util/stream/Stream.forEach:(Ljava/util/function/Consumer;)V
     42: aload_3
     43: ifnull        131
     46: aload         4
     48: ifnull        72
     51: aload_3
     52: invokeinterface #12,  1           // InterfaceMethod java/util/stream/Stream.close:()V
     57: goto          131
     60: astore        5
     62: aload         4
     64: aload         5
     66: invokevirtual #14                 // Method java/lang/Throwable.addSuppressed:(Ljava/lang/Throwable;)V
     69: goto          131
     72: aload_3
     73: invokeinterface #12,  1           // InterfaceMethod java/util/stream/Stream.close:()V
     78: goto          131
     81: astore        5
     83: aload         5
     85: astore        4
     87: aload         5
     89: athrow
     90: astore        6
     92: aload_3
     93: ifnull        128
     96: aload         4
     98: ifnull        122
    101: aload_3
    102: invokeinterface #12,  1           // InterfaceMethod java/util/stream/Stream.close:()V
    107: goto          128
    110: astore        7
    112: aload         4
    114: aload         7
    116: invokevirtual #14                 // Method java/lang/Throwable.addSuppressed:(Ljava/lang/Throwable;)V
    119: goto          128
    122: aload_3
    123: invokeinterface #12,  1           // InterfaceMethod java/util/stream/Stream.close:()V
    128: aload         6
    130: athrow
    131: getstatic     #15                 // Field java/lang/System.out:Ljava/io/PrintStream;
    134: aload_2
    135: invokevirtual #16                 // Method java/lang/StringBuilder.toString:()Ljava/lang/String;
    138: invokevirtual #17                 // Method java/io/PrintStream.println:(Ljava/lang/String;)V
    141: return
</code></pre><div class="line-numbers" aria-hidden="true"><div class="line-number"></div><div class="line-number"></div><div class="line-number"></div><div class="line-number"></div><div class="line-number"></div><div class="line-number"></div><div class="line-number"></div><div class="line-number"></div><div class="line-number"></div><div class="line-number"></div><div class="line-number"></div><div class="line-number"></div><div class="line-number"></div><div class="line-number"></div><div class="line-number"></div><div class="line-number"></div><div class="line-number"></div><div class="line-number"></div><div class="line-number"></div><div class="line-number"></div><div class="line-number"></div><div class="line-number"></div><div class="line-number"></div><div class="line-number"></div><div class="line-number"></div><div class="line-number"></div><div class="line-number"></div><div class="line-number"></div><div class="line-number"></div><div class="line-number"></div><div class="line-number"></div><div class="line-number"></div><div class="line-number"></div><div class="line-number"></div><div class="line-number"></div><div class="line-number"></div><div class="line-number"></div><div class="line-number"></div><div class="line-number"></div><div class="line-number"></div><div class="line-number"></div><div class="line-number"></div><div class="line-number"></div><div class="line-number"></div><div class="line-number"></div><div class="line-number"></div><div class="line-number"></div><div class="line-number"></div><div class="line-number"></div><div class="line-number"></div><div class="line-number"></div><div class="line-number"></div><div class="line-number"></div><div class="line-number"></div><div class="line-number"></div><div class="line-number"></div><div class="line-number"></div><div class="line-number"></div><div class="line-number"></div><div class="line-number"></div><div class="line-number"></div><div class="line-number"></div><div class="line-number"></div><div class="line-number"></div><div class="line-number"></div><div class="line-number"></div></div></div><p>\u6211\u4EEC\u53EF\u4EE5\u770B\u5230 <code>java/util/Stream</code>\u7684\u8C03\u7528\uFF0C\u901A\u8FC7<code>invokedynamic</code>\u5904\u7406\u4E86<code>Consumer</code>\u7C7B\u578B\u7684\u5BF9\u8C61\uFF0C<code>invokeinterface</code>\u4E3AStram.forEach \u8C03\u7528\uFF0C\u540E\u9762\u4F1A\u770B\u5230\u4E00\u4E9B <code>Stream.close:()V</code>\u548C<code>Method java/lang/Throwable.addSuppressed:(Ljava/lang/Throwable;)V</code>\u7684\u91CD\u590D\u8C03\u7528\uFF0C\u6B64\u5904\u5C31\u662F<code>try-with-resource</code>\u7528\u6765\u81EA\u52A8\u5173\u95ED\u6D41\u7684\u57FA\u672C\u903B\u8F91\u3002</p><p>\u603B\u7684\u6765\u8BF4\uFF0C\u8FD9\u662F\u4E00\u7BC7\u6BD4\u8F83\u4E0D\u9519\u7684\u5165\u95E8\u6587\u7AE0\uFF0C\u4F5C\u8005\u4EE5\u81EA\u8EAB\u7684\u6848\u4F8B\u6765\u8BF4\u660E\u5728\u65E5\u5E38\u5F00\u53D1\u4E2D\u5B57\u8282\u7801\u7684\u4F5C\u7528\uFF0C\u6587\u7AE0\u4E2D\u6240\u7528\u7684\u914D\u56FE\u4E5F\u5F88\u503C\u89C2\u6E05\u6670\u3002</p>`,13);function b(p,h){const n=v("ExternalLinkIcon");return d(),l("div",null,[e("blockquote",null,[e("p",null,[r,e("a",t,[u,o(n)])])]),m])}const _=i(c,[["render",b],["__file","jvm-byte-code.html.vue"]]);export{_ as default};
